ymci_ext_test_junit
