Metadata-Version: 1.1
Name: ymci-ext-test-junit
Version: 1.2
Summary: Junit test result plugin for ymci
Home-page: UNKNOWN
Author: Florian Mounier, Kozea
Author-email: florian.mounier@kozea.fr
License: UNKNOWN
Platform: Any
Provides: ymci_ext_test_junit
